Metadata-Version: 2.4
Name: adafruit-circuitpython-si1145
Version: 1.2.6
Summary: CircuitPython helper library for the SI1145 Digital UV Index IR Visible Light Sensor
Author-email: Adafruit Industries <circuitpython@adafruit.com>
License: MIT
Project-URL: Homepage, https://github.com/adafruit/Adafruit_CircuitPython_SI1145.git
Keywords: adafruit,blinka,circuitpython,micropython,si1145,ultraviolet,,infrared,,visible,,light
Classifier: Intended Audience :: Developers
Classifier: Topic :: Software Development :: Libraries
Classifier: Topic :: Software Development :: Embedded Systems
Classifier: Topic :: System :: Hardware
Classifier: License :: OSI Approved :: MIT License
Classifier: Programming Language :: Python :: 3
License-File: LICENSE
Requires-Dist: Adafruit-Blinka
Requires-Dist: adafruit-circuitpython-busdevice
Requires-Dist: adafruit-circuitpython-register
Provides-Extra: optional
Dynamic: license-file
